anaflow-1.2.0.dist-info/RECORD
anaflow-1.2.0.dist-info/WHEEL
anaflow-1.2.0.dist-info/top_level.txt
anaflow-1.2.0.dist-info/METADATA
anaflow-1.2.0.dist-info/licenses/LICENSE
anaflow/_version.py
anaflow/__init__.py
anaflow/tools/laplace.py
anaflow/tools/coarse_graining.py
anaflow/tools/__init__.py
anaflow/tools/mean.py
anaflow/tools/special.py
anaflow/flow/laplace.py
anaflow/flow/ext_grf_model.py
anaflow/flow/_laplace_accel.cpython-313-darwin.so
anaflow/flow/__init__.py
anaflow/flow/_laplace_accel.pyx
anaflow/flow/homogeneous.py
anaflow/flow/heterogeneous.py
