Metadata-Version: 2.4
Name: anaflow
Version: 1.2.0
Summary: AnaFlow - analytical solutions for the groundwater-flow equation.
Author-email: Sebastian Mueller <sebastian.mueller@ufz.de>
License-Expression: MIT
Project-URL: Homepage, https://github.com/GeoStat-Framework/AnaFlow
Project-URL: Documentation, https://anaflow.readthedocs.io
Project-URL: Source, https://github.com/GeoStat-Framework/anaflow
Project-URL: Tracker, https://github.com/GeoStat-Framework/anaflow/issues
Project-URL: Changelog, https://github.com/GeoStat-Framework/anaflow/blob/main/CHANGELOG.md
Project-URL: Conda-Forge, https://anaconda.org/conda-forge/anaflow
Classifier: Development Status :: 5 - Production/Stable
Classifier: Intended Audience :: Developers
Classifier: Intended Audience :: End Users/Desktop
Classifier: Intended Audience :: Science/Research
Classifier: Natural Language :: English
Classifier: Operating System :: MacOS
Classifier: Operating System :: MacOS :: MacOS X
Classifier: Operating System :: Microsoft
Classifier: Operating System :: Microsoft :: Windows
Classifier: Operating System :: POSIX
Classifier: Operating System :: Unix
Classifier: Programming Language :: Python
Classifier: Programming Language :: Python :: 3
Classifier: Programming Language :: Python :: 3 :: Only
Classifier: Programming Language :: Python :: 3.9
Classifier: Programming Language :: Python :: 3.10
Classifier: Programming Language :: Python :: 3.11
Classifier: Programming Language :: Python :: 3.12
Classifier: Programming Language :: Python :: 3.13
Classifier: Programming Language :: Python :: 3.14
Classifier: Topic :: Scientific/Engineering
Classifier: Topic :: Software Development
Classifier: Topic :: Utilities
Requires-Python: >=3.9
License-File: LICENSE
Requires-Dist: numpy>=1.20.0
Requires-Dist: pentapy<2,>=1.1.0
Requires-Dist: scipy>=1.5.4
Provides-Extra: doc
Requires-Dist: myst-parser; extra == "doc"
Requires-Dist: matplotlib>=3.7; extra == "doc"
Requires-Dist: numpydoc>=1.1; extra == "doc"
Requires-Dist: sphinx>=7; extra == "doc"
Requires-Dist: sphinx-gallery>=0.8; extra == "doc"
Requires-Dist: sphinx-rtd-theme>=3; extra == "doc"
Provides-Extra: test
Requires-Dist: pytest-cov>=3; extra == "test"
Provides-Extra: check
Requires-Dist: black>=25; extra == "check"
Requires-Dist: isort[colors]; extra == "check"
Requires-Dist: ruff>=0.5.0; extra == "check"
Requires-Dist: cython-lint; extra == "check"
Dynamic: license-file
